opencode_bridge/__init__.py
opencode_bridge/install.py
opencode_bridge/server.py
opencode_bridge-0.1.5.dist-info/METADATA
opencode_bridge-0.1.5.dist-info/WHEEL
opencode_bridge-0.1.5.dist-info/entry_points.txt
opencode_bridge-0.1.5.dist-info/RECORD
