Metadata-Version: 2.4
Name: opencode-bridge
Version: 0.1.5
Summary: MCP server for continuous OpenCode discussion sessions
Project-URL: Repository, https://github.com/genomewalker/opencode-bridge
Author: Antonio Fernandez-Guerra
License-Expression: MIT
Keywords: claude,code-review,discussion,gpt,mcp,opencode
Classifier: Development Status :: 4 - Beta
Classifier: Environment :: Console
Classifier: Intended Audience :: Developers
Classifier: License :: OSI Approved :: MIT License
Classifier: Programming Language :: Python :: 3.10
Classifier: Programming Language :: Python :: 3.11
Classifier: Programming Language :: Python :: 3.12
Requires-Python: >=3.10
Requires-Dist: mcp>=1.0.0
Provides-Extra: dev
Requires-Dist: pytest>=8.0.0; extra == 'dev'
Requires-Dist: ruff>=0.4.0; extra == 'dev'
